scorescanner/__init__.py
scorescanner/data/__init__.py
scorescanner/data/adult_data.csv
scorescanner/data/credit_score_train.csv
scorescanner/feature_selection/__init__.py
scorescanner/feature_selection/_data.py
scorescanner/preprocessing/__init__.py
scorescanner/preprocessing/_data.py
scorescanner/utils/__init__.py
scorescanner/utils/plotting.py
scorescanner/utils/statistical_metrics.py
tests/__init__.py
tests/preprocessing/__init__.py
tests/preprocessing/_data_tests.py
tests/utils/__init__.py
tests/utils/statistical_metrics_tests.py
tutorials/__init__.py
tutorials/utils.py
scorescanner-0.1.3.dist-info/LICENSE
scorescanner-0.1.3.dist-info/METADATA
scorescanner-0.1.3.dist-info/WHEEL
scorescanner-0.1.3.dist-info/top_level.txt
scorescanner-0.1.3.dist-info/RECORD
