Metadata-Version: 2.1
Name: scorescanner
Version: 0.1.3
Summary: scorescanner streamline the exploration and quantification of relationships between features and the target in a context of predictive Machine Learning models.
Home-page: UNKNOWN
Author: Imad Berkani
Author-email: berkaniimad75@gmail.com
License: MIT
Platform: UNKNOWN
Classifier: Programming Language :: Python :: 3
Classifier: Programming Language :: Python :: 3.8
Classifier: Programming Language :: Python :: 3.9
Classifier: Programming Language :: Python :: 3.10
Classifier: Operating System :: OS Independent
Requires-Dist: matplotlib
Requires-Dist: numpy >=1.26.4
Requires-Dist: optbinning >=0.19.0
Requires-Dist: pandas >=1.5.3
Requires-Dist: plotly >=5.18.0
Requires-Dist: ppscore >=1.3.0
Requires-Dist: scikit-learn >=1.4.0
Requires-Dist: scipy >=1.12.0
Requires-Dist: statsmodels >=0.14.1
Requires-Dist: tqdm >=4.66.1
Requires-Dist: jinja2 ==3.0.1
